{
  "area" : "Domaine 3",
  "title": "Utiliser un TBI/TNI",
  "description": "Au programme de cette vidéo : explication sur le fonctionnement d'un tableau numérique interactif et quelques exemples de fonctionnalités.",
  "videoEmbedSrc": "https://tube-numerique-educatif.apps.education.fr/videos/embed/fe0505f0-6237-4818-ba2b-54c110dc47b3",
  "videoDLHref": "https://tube-numerique-educatif.apps.education.fr/download/videos/fe0505f0-6237-4818-ba2b-54c110dc47b3-1080.mp4",
  "fichePdfHref": "",
  "transcriptPdfHref": ""
}
